{
  "version": 1,
  "assignments": [
    {
      "hw_id": 1,
      "follow": 0,
      "offset_x": 0.0,
      "offset_y": 0.0,
      "offset_z": 0.0,
      "frame": "ned"
    },
    {
      "hw_id": 2,
      "follow": 1,
      "offset_x": -3.0,
      "offset_y": -3.0,
      "offset_z": 0.25,
      "frame": "ned"
    },
    {
      "hw_id": 3,
      "follow": 1,
      "offset_x": 3.0,
      "offset_y": 3.0,
      "offset_z": 0.5,
      "frame": "ned"
    },
    {
      "hw_id": 4,
      "follow": 1,
      "offset_x": -3.0,
      "offset_y": 3.0,
      "offset_z": 0.75,
      "frame": "ned"
    },
    {
      "hw_id": 5,
      "follow": 0,
      "offset_x": 0.0,
      "offset_y": 0.0,
      "offset_z": 1.0,
      "frame": "ned"
    },
    {
      "hw_id": 6,
      "follow": 5,
      "offset_x": -3.0,
      "offset_y": -3.0,
      "offset_z": 1.25,
      "frame": "ned"
    },
    {
      "hw_id": 7,
      "follow": 5,
      "offset_x": 3.0,
      "offset_y": 3.0,
      "offset_z": 1.5,
      "frame": "ned"
    },
    {
      "hw_id": 8,
      "follow": 5,
      "offset_x": -3.0,
      "offset_y": 3.0,
      "offset_z": 1.75,
      "frame": "ned"
    },
    {
      "hw_id": 9,
      "follow": 0,
      "offset_x": 0.0,
      "offset_y": 0.0,
      "offset_z": 2.0,
      "frame": "ned"
    },
    {
      "hw_id": 10,
      "follow": 9,
      "offset_x": -3.0,
      "offset_y": -3.0,
      "offset_z": 2.25,
      "frame": "ned"
    },
    {
      "hw_id": 11,
      "follow": 9,
      "offset_x": 3.0,
      "offset_y": 3.0,
      "offset_z": 2.5,
      "frame": "ned"
    },
    {
      "hw_id": 12,
      "follow": 9,
      "offset_x": -3.0,
      "offset_y": 3.0,
      "offset_z": 2.75,
      "frame": "ned"
    },
    {
      "hw_id": 13,
      "follow": 2,
      "offset_x": -2.0,
      "offset_y": 1.2,
      "offset_z": 3.0,
      "frame": "ned"
    },
    {
      "hw_id": 14,
      "follow": 6,
      "offset_x": 3.0,
      "offset_y": 5.0,
      "offset_z": 3.25,
      "frame": "ned"
    },
    {
      "hw_id": 15,
      "follow": 9,
      "offset_x": 4.0,
      "offset_y": 10.0,
      "offset_z": 3.5,
      "frame": "ned"
    },
    {
      "hw_id": 16,
      "follow": 1,
      "offset_x": 5.0,
      "offset_y": 2.0,
      "offset_z": 3.75,
      "frame": "ned"
    }
  ]
}
